context_bus/__init__.py
context_bus/cli.py
context_bus/config.template.yaml
context_bus/scripts/auto-update-task.sh
context_bus/scripts/check-usage.sh
context_bus/scripts/context-handoff.sh
context_bus/scripts/generate-summary.sh
context_bus/scripts/handoff-utils.sh
context_bus/scripts/kimi-summarize.sh
context_bus/scripts/model-router.sh
context_bus/scripts/refresh-summary.sh
context_bus/scripts/semantic-context.sh
context_bus/scripts/setup.sh
context_bus/scripts/update-handoff.sh
context_bus/scripts/update-state.sh
context_bus/scripts/update-usage.sh
context_bus/scripts/usage-monitor.sh
context_bus/templates/AGENTS.md
context_bus/templates/MEMORY.md
context_bus-0.2.1.dist-info/licenses/LICENSE
context_bus-0.2.1.dist-info/METADATA
context_bus-0.2.1.dist-info/WHEEL
context_bus-0.2.1.dist-info/entry_points.txt
context_bus-0.2.1.dist-info/top_level.txt
context_bus-0.2.1.dist-info/RECORD
