Metadata-Version: 2.4
Name: context-bus
Version: 0.2.1
Summary: Automatic model switching for AI coding agents with full context preservation
Author-email: Rajath KM <rajathkm@gmail.com>
License: MIT
Project-URL: Homepage, https://github.com/rajathkm/context-bus
Project-URL: Documentation, https://github.com/rajathkm/context-bus#readme
Project-URL: Repository, https://github.com/rajathkm/context-bus
Project-URL: Issues, https://github.com/rajathkm/context-bus/issues
Keywords: ai,llm,claude,codex,gemini,model-switching,context
Classifier: Development Status :: 4 - Beta
Classifier: Intended Audience :: Developers
Classifier: License :: OSI Approved :: MIT License
Classifier: Operating System :: OS Independent
Classifier: Programming Language :: Python :: 3
Classifier: Programming Language :: Python :: 3.8
Classifier: Programming Language :: Python :: 3.9
Classifier: Programming Language :: Python :: 3.10
Classifier: Programming Language :: Python :: 3.11
Classifier: Programming Language :: Python :: 3.12
Classifier: Topic :: Software Development :: Libraries :: Python Modules
Requires-Python: >=3.8
License-File: LICENSE
Requires-Dist: pyyaml>=6.0
Requires-Dist: click>=8.0
Provides-Extra: dev
Requires-Dist: pytest>=7.0; extra == "dev"
Requires-Dist: black>=23.0; extra == "dev"
Dynamic: license-file
